LICENSE
MANIFEST.in
README.md
setup.cfg
setup.py
my_sample/__init__.py
my_sample.egg-info/PKG-INFO
my_sample.egg-info/SOURCES.txt
my_sample.egg-info/dependency_links.txt
my_sample.egg-info/top_level.txt