Metadata-Version: 1.1
Name: my-sample
Version: 0.4.0
Summary: Not the most useful package
Home-page: https://github.com/kylebebak/my_sample
Author: kylebebak
Author-email: kylebebak@gmail.com
License: MIT
Download-URL: https://github.com/kylebebak/my_sample/tarball/0.4.0
Keywords: sample pip tutorial
Platform: UNKNOWN
Classifier: Intended Audience :: Developers
Classifier: License :: OSI Approved :: MIT License
Classifier: Programming Language :: Python
